solc_event_extractor/__init__.py
solc_event_extractor/parser.py
solc_event_extractor/types.py
solc_event_extractor-0.1.0.dist-info/METADATA
solc_event_extractor-0.1.0.dist-info/WHEEL
solc_event_extractor-0.1.0.dist-info/RECORD
