Metadata-Version: 2.3
Name: solc-event-extractor
Version: 0.1.0
Summary: Add your description here
Author-email: Evan K <ekcopersonal@gmail.com>
Requires-Python: >=3.12
Requires-Dist: py-solc-x>=2.0.3
